langfuse_sdk/__init__.py
langfuse_sdk/_task_manager/ingestion_consumer.py
langfuse_sdk/_task_manager/media_manager.py
langfuse_sdk/_task_manager/media_upload_consumer.py
langfuse_sdk/_task_manager/media_upload_queue.py
langfuse_sdk/_task_manager/task_manager.py
langfuse_sdk/api/__init__.py
langfuse_sdk/api/client.py
langfuse_sdk/api/core/__init__.py
langfuse_sdk/api/core/api_error.py
langfuse_sdk/api/core/client_wrapper.py
langfuse_sdk/api/core/datetime_utils.py
langfuse_sdk/api/core/file.py
langfuse_sdk/api/core/http_client.py
langfuse_sdk/api/core/jsonable_encoder.py
langfuse_sdk/api/core/pydantic_utilities.py
langfuse_sdk/api/core/query_encoder.py
langfuse_sdk/api/core/remove_none_from_dict.py
langfuse_sdk/api/core/request_options.py
langfuse_sdk/api/README.md
langfuse_sdk/api/reference.md
langfuse_sdk/api/resources/__init__.py
langfuse_sdk/api/resources/annotation_queues/__init__.py
langfuse_sdk/api/resources/annotation_queues/client.py
langfuse_sdk/api/resources/annotation_queues/types/__init__.py
langfuse_sdk/api/resources/annotation_queues/types/annotation_queue.py
langfuse_sdk/api/resources/annotation_queues/types/annotation_queue_item.py
langfuse_sdk/api/resources/annotation_queues/types/annotation_queue_object_type.py
langfuse_sdk/api/resources/annotation_queues/types/annotation_queue_status.py
langfuse_sdk/api/resources/annotation_queues/types/create_annotation_queue_item_request.py
langfuse_sdk/api/resources/annotation_queues/types/delete_annotation_queue_item_response.py
langfuse_sdk/api/resources/annotation_queues/types/paginated_annotation_queue_items.py
langfuse_sdk/api/resources/annotation_queues/types/paginated_annotation_queues.py
langfuse_sdk/api/resources/annotation_queues/types/update_annotation_queue_item_request.py
langfuse_sdk/api/resources/comments/__init__.py
langfuse_sdk/api/resources/comments/client.py
langfuse_sdk/api/resources/comments/types/__init__.py
langfuse_sdk/api/resources/comments/types/create_comment_request.py
langfuse_sdk-1.0.0.dist-info/entry_points.txt
langfuse_sdk-1.0.0.dist-info/LICENSE
langfuse_sdk-1.0.0.dist-info/METADATA
langfuse_sdk-1.0.0.dist-info/WHEEL
langfuse_sdk-1.0.0.dist-info/RECORD
